langframe-0.4.0.dist-info/METADATA
langframe-0.4.0.dist-info/WHEEL
langframe-0.4.0.dist-info/licenses/LICENSE
langframe/__init__.py
langframe/_backends/__init__.py
langframe/_backends/base/__init__.py
langframe/_backends/base/catalog.py
langframe/_backends/base/execution.py
langframe/_backends/base/lineage.py
langframe/_backends/base/session_state.py
langframe/_backends/cloud/__init__.py
langframe/_backends/cloud/catalog.py
langframe/_backends/cloud/engine_config.py
langframe/_backends/cloud/execution.py
langframe/_backends/cloud/manager.py
langframe/_backends/cloud/session_state.py
langframe/_backends/cloud/settings.py
langframe/_backends/local/__init__.py
langframe/_backends/local/catalog.py
langframe/_backends/local/execution.py
langframe/_backends/local/lineage.py
langframe/_backends/local/manager.py
langframe/_backends/local/physical_plan/__init__.py
langframe/_backends/local/physical_plan/aggregate.py
langframe/_backends/local/physical_plan/base.py
langframe/_backends/local/physical_plan/join.py
langframe/_backends/local/physical_plan/sink.py
langframe/_backends/local/physical_plan/source.py
langframe/_backends/local/physical_plan/transform.py
langframe/_backends/local/polars_plugins/__init__.py
langframe/_backends/local/polars_plugins/chunking.py
langframe/_backends/local/polars_plugins/markdown.py
langframe/_backends/local/polars_plugins/tokenization.py
langframe/_backends/local/polars_plugins/transcripts.py
langframe/_backends/local/schema_storage.py
langframe/_backends/local/semantic_operators/__init__.py
langframe/_backends/local/semantic_operators/analyze_sentiment.py
langframe/_backends/local/semantic_operators/base.py
langframe/_backends/local/semantic_operators/classify.py
langframe/_backends/local/semantic_operators/cluster.py
langframe/_backends/local/semantic_operators/extract.py
langframe/_backends/local/semantic_operators/join.py
langframe/_backends/local/semantic_operators/map.py
langframe/_backends/local/semantic_operators/predicate.py
langframe/_backends/local/semantic_operators/reduce.py
langframe/_backends/local/semantic_operators/sim_join.py
langframe-0.4.0.dist-info/RECORD
