Metadata-Version: 2.4
Name: langframe
Version: 0.4.0
Classifier: Programming Language :: Python :: 3
Classifier: Operating System :: OS Independent
Requires-Dist: boto3>=1.38.28
Requires-Dist: botocore>=1.38.28
Requires-Dist: duckdb>=1.1.3
Requires-Dist: numpy>=2.0.0
Requires-Dist: openai>=1.60.1
Requires-Dist: pandas>=2.2.2
Requires-Dist: polars>=1.20.0
Requires-Dist: tiktoken>=0.9.0
Requires-Dist: pylance>=0.23.2
Requires-Dist: lancedb>=0.22.0
Requires-Dist: pyarrow>=19.0.0,<20.0.0 ; extra == 'cloud'
Requires-Dist: grpcio>=1.60.0 ; extra == 'cloud'
Requires-Dist: pydantic-settings ; extra == 'cloud'
Requires-Dist: langframe-cloud>=0.1.1 ; extra == 'cloud'
Provides-Extra: cloud
License-File: LICENSE
Summary: langframe is a Python DataFrame library for processing text data with APIs inspired by PySpark.
